README.rst
setup.py
bitcustody_client.egg-info/PKG-INFO
bitcustody_client.egg-info/SOURCES.txt
bitcustody_client.egg-info/dependency_links.txt
bitcustody_client.egg-info/not-zip-safe
bitcustody_client.egg-info/top_level.txt
foo/__init__.py